spacetower_python_client/__init__.py
spacetower_python_client/api/__init__.py
spacetower_python_client/api/battery_api.py
spacetower_python_client/api/covariance_matrix_api.py
spacetower_python_client/api/ephemeris_request_controller_api.py
spacetower_python_client/api/events_request_api.py
spacetower_python_client/api/ground_station_api.py
spacetower_python_client/api/maneuver_generation_api.py
spacetower_python_client/api/maneuver_strategy_api.py
spacetower_python_client/api/measurements_request_api.py
spacetower_python_client/api/orbit_api.py
spacetower_python_client/api/orbit_data_message_request_api.py
spacetower_python_client/api/orbit_determination_api.py
spacetower_python_client/api/orbit_determination_configuration_api.py
spacetower_python_client/api/orbit_extrapolation_api.py
spacetower_python_client/api/orbital_state_api.py
spacetower_python_client/api/parameter_estimation_request_api.py
spacetower_python_client/api/propagation_context_api.py
spacetower_python_client/api/roadmap_action_api.py
spacetower_python_client/api/roadmap_api.py
spacetower_python_client/api/solar_array_api.py
spacetower_python_client/api/spacecraft_api.py
spacetower_python_client/api/telemetry_api.py
spacetower_python_client/api/thruster_api.py
spacetower_python_client/api/tlesgp4_extrapolation_api.py
spacetower_python_client/api_client.py
spacetower_python_client/api_response.py
spacetower_python_client/configuration.py
spacetower_python_client/exceptions.py
spacetower_python_client/models/__init__.py
spacetower_python_client/models/attitude_action_dto.py
spacetower_python_client/models/battery_dto.py
spacetower_python_client/models/box_spacecraft_input_dto.py
spacetower_python_client/models/cartesian_orbit_dto.py
spacetower_python_client/models/chemical_thruster_dto.py
spacetower_python_client/models/circular_orbit_dto.py
spacetower_python_client/models/create_ukf_orbit_determination_configuration200_response.py
spacetower_python_client/models/date_interval_dto.py
spacetower_python_client-1.1.2.dist-info/METADATA
spacetower_python_client-1.1.2.dist-info/WHEEL
spacetower_python_client-1.1.2.dist-info/RECORD
